odoo/addons/mail_message_search/README.rst
odoo/addons/mail_message_search/__init__.py
odoo/addons/mail_message_search/__manifest__.py
odoo/addons/mail_message_search/i18n/it.po
odoo/addons/mail_message_search/i18n/mail_message_search.pot
odoo/addons/mail_message_search/models/__init__.py
odoo/addons/mail_message_search/models/mail_thread.py
odoo/addons/mail_message_search/readme/CONFIGURE.md
odoo/addons/mail_message_search/readme/CONTEXT.md
odoo/addons/mail_message_search/readme/CONTRIBUTORS.md
odoo/addons/mail_message_search/readme/DESCRIPTION.md
odoo/addons/mail_message_search/readme/USAGE.md
odoo/addons/mail_message_search/static/description/icon.png
odoo/addons/mail_message_search/static/description/index.html
odoo/addons/mail_message_search/tests/__init__.py
odoo/addons/mail_message_search/tests/test_mail_message_search.py
odoo_addon_mail_message_search-18.0.1.0.2.dist-info/METADATA
odoo_addon_mail_message_search-18.0.1.0.2.dist-info/WHEEL
odoo_addon_mail_message_search-18.0.1.0.2.dist-info/top_level.txt
odoo_addon_mail_message_search-18.0.1.0.2.dist-info/RECORD
