Metadata-Version: 2.1
Name: odoo-addon-mail_message_search
Version: 18.0.1.0.2
Requires-Python: >=3.10
Requires-Dist: odoo==18.0.*
Summary: Mail Message Search
Home-page: https://github.com/OCA/mail
License: AGPL-3
Author: Quartile, Odoo Community Association (OCA)
Author-email: support@odoo-community.org
Classifier: Programming Language :: Python
Classifier: Framework :: Odoo
Classifier: Framework :: Odoo :: 18.0
Classifier: License :: OSI Approved :: GNU Affero General Public License v3
